ddparser/__init__.py
ddparser/run.py
ddparser/run_test.py
ddparser/ernie/__init__.py
ddparser/ernie/file_utils.py
ddparser/ernie/modeling_ernie.py
ddparser/ernie/optimization.py
ddparser/ernie/tokenizing_ernie.py
ddparser/parser/__init__.py
ddparser/parser/config.py
ddparser/parser/model.py
ddparser/parser/model_test.py
ddparser/parser/data_struct/__init__.py
ddparser/parser/data_struct/corpus.py
ddparser/parser/data_struct/data.py
ddparser/parser/data_struct/embedding.py
ddparser/parser/data_struct/field.py
ddparser/parser/data_struct/metric.py
ddparser/parser/data_struct/utils.py
ddparser/parser/data_struct/vocab.py
ddparser/parser/nets/__init__.py
ddparser/parser/nets/biaffine.py
ddparser/parser/nets/bilstm.py
ddparser/parser/nets/char_lstm.py
ddparser/parser/nets/char_transformer.py
ddparser/parser/nets/dropouts.py
ddparser/parser/nets/embedding.py
ddparser/parser/nets/mlp.py
ddparser/parser/nets/nn.py
ddparser/parser/nets/rnn.py
ddparser/parser/nets/transformer.py
ddparser_test/__init__.py
ddparser_test/run.py
ddparser_test/ernie/__init__.py
ddparser_test/ernie/file_utils.py
ddparser_test/ernie/modeling_ernie.py
ddparser_test/ernie/optimization.py
ddparser_test/ernie/tokenizing_ernie.py
ddparser_test/parser/__init__.py
ddparser_test/parser/config.py
ddparser_test/parser/model.py
ddparser_test/parser/data_struct/__init__.py
ddparser_test/parser/data_struct/corpus.py
ddparser_test/parser/data_struct/data.py
ddparser_test/parser/data_struct/embedding.py
ddparser_test/parser/data_struct/field.py
ddparser_test/parser/data_struct/metric.py
ddparser_test/parser/data_struct/utils.py
ddparser_test/parser/data_struct/vocab.py
ddparser_test/parser/nets/__init__.py
ddparser_test/parser/nets/biaffine.py
ddparser_test/parser/nets/bilstm.py
ddparser_test/parser/nets/char_lstm.py
ddparser_test/parser/nets/char_transformer.py
ddparser_test/parser/nets/dropouts.py
ddparser_test/parser/nets/embedding.py
ddparser_test/parser/nets/mlp.py
ddparser_test/parser/nets/nn.py
ddparser-1.0.8.dist-info/LICENSE
ddparser-1.0.8.dist-info/METADATA
ddparser-1.0.8.dist-info/WHEEL
ddparser-1.0.8.dist-info/top_level.txt
ddparser-1.0.8.dist-info/RECORD
