Metadata-Version: 2.1
Name: ddparser
Version: 1.0.8
Summary: A chinese dependency parser tool by Baidu NLP.
Home-page: https://github.com/baidu/ddparser
Author: Baidu NLP
Author-email: nlp-parser@baidu.com
License: Apache 2.0
Keywords: ddparser chinese depencency parser
Platform: any
Classifier: License :: OSI Approved :: Apache Software License
Classifier: Programming Language :: Python
Classifier: Programming Language :: Python :: 3.7
Classifier: Programming Language :: Python :: 3.8
Requires-Python: >=3.7
License-File: LICENSE
